llm_evals/__init__.py
llm_evals/checks.py
llm_evals/hookspecs.py
llm_evals_plugin-0.1a0.dist-info/METADATA
llm_evals_plugin-0.1a0.dist-info/WHEEL
llm_evals_plugin-0.1a0.dist-info/entry_points.txt
llm_evals_plugin-0.1a0.dist-info/top_level.txt
llm_evals_plugin-0.1a0.dist-info/RECORD
