Metadata-Version: 2.1
Name: llm-evals-plugin
Version: 0.1a0
Summary: Run evals against prompts using LLM
Author: Simon Willison
License: Apache-2.0
Project-URL: Homepage, https://github.com/simonw/llm-evals-plugin
Project-URL: Changelog, https://github.com/simonw/llm-evals-plugin/releases
Project-URL: Issues, https://github.com/simonw/llm-evals-plugin/issues
Project-URL: CI, https://github.com/simonw/llm-evals-plugin/actions
Classifier: License :: OSI Approved :: Apache Software License
Requires-Dist: llm
Provides-Extra: test
Requires-Dist: pytest ; extra == 'test'
